django_nepali/__init__.py
django_nepali/templatetags/__init__.py
django_nepali/templatetags/nepalidatetime.py
django_nepali/templatetags/nepalinumber.py
django_nepali-0.1.0.dist-info/LICENSE
django_nepali-0.1.0.dist-info/METADATA
django_nepali-0.1.0.dist-info/WHEEL
django_nepali-0.1.0.dist-info/top_level.txt
django_nepali-0.1.0.dist-info/RECORD
