Metadata-Version: 2.1
Name: django-nepali
Version: 0.1.0
Summary: A django package on top of 'nepali' a python package which supports nepali date time, time conversion, etc on django projects.
Home-page: https://github.com/opensource-nepal/django-nepali
Author: opensource-nepal
Author-email: aj3sshh@gmail.com, sugatbajracharya49@gmail.com
Keywords: django,nepali date conversion,convert date,nepali date time,python convert date,parse nepali date time
Classifier: Programming Language :: Python :: 3
Classifier: License :: OSI Approved :: GNU General Public License (GPL)
Classifier: Environment :: Web Environment
Classifier: Operating System :: OS Independent
Classifier: Framework :: Django
License-File: LICENSE
Requires-Dist: django
Requires-Dist: nepali (>=1.0.0)
